mt5linux/__init__.py
mt5linux/__main__.py
MT5LinuxEnhanced-0.3.1.dist-info/LICENSE.txt
MT5LinuxEnhanced-0.3.1.dist-info/METADATA
MT5LinuxEnhanced-0.3.1.dist-info/WHEEL
MT5LinuxEnhanced-0.3.1.dist-info/top_level.txt
MT5LinuxEnhanced-0.3.1.dist-info/RECORD
