Metadata-Version: 2.1
Name: MT5LinuxEnhanced
Version: 0.3.1
Summary: MetaTrader5 for Linux users, improved version
Home-page: https://github.com/kusmin/MT5LinuxEnhanced
Author: Lucas Prett Campagna, Renan Ribeiro Lage
License: MIT
License-File: LICENSE.txt
Requires-Dist: numpy
Requires-Dist: plumbum ==1.8.3
Requires-Dist: pyparsing ==3.1.2
Requires-Dist: rpyc ==6.0.0
